loga/__init__.py
loga/_loga.py
loga/py.typed
loga-1.0.0.dist-info/LICENSE
loga-1.0.0.dist-info/WHEEL
loga-1.0.0.dist-info/METADATA
loga-1.0.0.dist-info/RECORD
