Metadata-Version: 2.1
Name: loga
Version: 1.0.0
Summary: Automated logging for Python
Home-page: https://github.com/hukkinj1/loga
License: MIT
Keywords: logging,graylog
Author: hukkinj1
Author-email: hukkinj1@users.noreply.github.com
Requires-Python: >=3.8,<4.0
Classifier: License :: OSI Approved :: MIT License
Classifier: Programming Language :: Python :: 3
Classifier: Programming Language :: Python :: 3.8
Classifier: Topic :: Software Development :: Libraries :: Python Modules
Classifier: Typing :: Typed
Provides-Extra: graylog
Requires-Dist: graypy (>=2,<3); extra == "graylog"
Project-URL: Changelog, https://github.com/hukkinj1/loga/blob/master/CHANGELOG.md
Project-URL: Repository, https://github.com/hukkinj1/loga
